scarlex/__init__.py
scarlex/__main__.py
scarlex-1.0.2.dist-info/LICENSE
scarlex-1.0.2.dist-info/METADATA
scarlex-1.0.2.dist-info/WHEEL
scarlex-1.0.2.dist-info/top_level.txt
scarlex-1.0.2.dist-info/RECORD
