Metadata-Version: 2.1
Name: scarlex
Version: 1.0.2
Summary: Scarlex API Wrapper
Home-page: https://github.com/ScarlexDev/ScarlexPY
Author: avixity
License: Apache 2.0
Keywords: scarlex,api
Platform: UNKNOWN
Classifier: Programming Language :: Python :: 3
Classifier: License :: OSI Approved :: Apache Software License
Classifier: Operating System :: OS Independent
License-File: LICENSE
Requires-Dist: aiohttp
